pythonPlayGround
