Metadata-Version: 1.1
Name: pythonPlayGround
Version: 0.3
Summary: play ground for python
Home-page: http://rkalva89828.kau.roche.com/daij12/pythonPlayGround
Author: Jian Dai
Author-email: daij12@gene.com
License: MIT
Keywords: test internal
Platform: UNKNOWN
Classifier: Development Status :: 3 - Alpha
Classifier: License :: OSI Approved :: MIT License
Classifier: Programming Language :: Python :: 2.7
Classifier: Topic :: Text Processing :: Linguistic
